{"elec": "1", "amb": "21", "tope": "1", "numact": "19", "numdep": "19", "iscircus": "0", "mdhm": "05311738", "shc": "0", "totales": {"act": {"metota": "3228", "mesesc": "3228", "pmesesc": "100%", "meserr": "0", "centota": "1089418", "carg": "0", "cargElectos": "0", "cargEmpatados": "0", "cargtota": "0", "votant": "507993", "pvotant": "46,62%", "absten": "581425", "pabsten": "53,37%", "votnul": "3712", "pvotnul": "0,73%", "votnma": "1091", "pvotnma": "0,21%", "votblan": "7556", "pvotblan": "1,50%", "votval": "503190", "pvotval": "99,05%"}}, "camaras": [{"cam": "0", "cir": "0", "carg": "0", "cargElectos": "0", "cargEmpatados": "0", "cargtota": "", "totales": {"act": {"votant": "507993", "pvotant": "46,62%", "votnul": "3712", "pvotnul": "0,73%", "votnma": "1091", "pvotnma": "0,21%", "votbla": "7556", "pvotbla": "1,50%", "votcan": "495634", "pvotcan": "98,49%", "votval": "503190", "pvotval": "99,05%", "pvotcam": "0%"}}, "partotabla": [{"act": {"codpar": "7", "cam": "0", "vot": "263014", "pvot": "52,26%", "carg": "0", "cargElectos": "0", "cargEmpatados": "0", "cantotabla": [{"amb": "21", "codcan": "1", "sorteo": "1", "cedula": "79262397", "nomcan": "IVÁN", "apecan": "CEPEDA CASTRO", "nomcan2": "AIDA MARINA", "apecan2": "QUILCUE VIVAS", "vot": "263014", "pvot": "52,26%", "carg": "0", "pref": "1", "empate": "0"}]}}, {"act": {"codpar": "10", "cam": "0", "vot": "197533", "pvot": "39,25%", "carg": "0", "cargElectos": "0", "cargEmpatados": "0", "cantotabla": [{"amb": "21", "codcan": "4", "sorteo": "5", "cedula": "11004242", "nomcan": "ABELARDO", "apecan": "DE LA ESPRIELLA", "nomcan2": "JOSÉ MANUEL", "apecan2": "RESTREPO ABONDANO", "vot": "197533", "pvot": "39,25%", "carg": "0", "pref": "1", "empate": "0"}]}}, {"act": {"codpar": "2", "cam": "0", "vot": "18398", "pvot": "3,65%", "carg": "0", "cargElectos": "0", "cargEmpatados": "0", "cantotabla": [{"amb": "21", "codcan": "11", "sorteo": "12", "cedula": "25280205", "nomcan": "PALOMA", "apecan": "VALENCIA LASERNA", "nomcan2": "JUAN DANIEL", "apecan2": "OVIEDO ARANGO", "vot": "18398", "pvot": "3,65%", "carg": "0", "pref": "1", "empate": "0"}]}}, {"act": {"codpar": "3", "cam": "0", "vot": "7934", "pvot": "1,57%", "carg": "0", "cargElectos": "0", "cargEmpatados": "0", "cantotabla": [{"amb": "21", "codcan": "12", "sorteo": "13", "cedula": "70546658", "nomcan": "SERGIO", "apecan": "FAJARDO VALDERRAMA", "nomcan2": "EDNA CRISTINA", "apecan2": "DEL SOCORRO BONILLA SEBA", "vot": "7934", "pvot": "1,57%", "carg": "0", "pref": "1", "empate": "0"}]}}, {"act": {"codpar": "8", "cam": "0", "vot": "2679", "pvot": "0,53%", "carg": "0", "cargElectos": "0", "cargEmpatados": "0", "cantotabla": [{"amb": "21", "codcan": "3", "sorteo": "4", "cedula": "98567762", "nomcan": "RAÚL SANTIAGO", "apecan": "BOTERO JARAMILLO", "nomcan2": "CARLOS FERNANDO", "apecan2": "CUEVAS ROMERO", "vot": "2679", "pvot": "0,53%", "carg": "0", "pref": "1", "empate": "0"}]}}, {"act": {"codpar": "13", "cam": "0", "vot": "2510", "pvot": "0,49%", "carg": "0", "cargElectos": "0", "cargEmpatados": "0", "cantotabla": [{"amb": "21", "codcan": "9", "sorteo": "10", "cedula": "85448338", "nomcan": "CARLOS EDUARDO", "apecan": "CAICEDO OMAR", "nomcan2": "NELSON JAVIER", "apecan2": "ALARCÓN SUÁREZ", "vot": "2510", "pvot": "0,49%", "carg": "0", "pref": "1", "empate": "0"}]}}, {"act": {"codpar": "11", "cam": "0", "vot": "1229", "pvot": "0,24%", "carg": "0", "cargElectos": "0", "cargEmpatados": "0", "cantotabla": [{"amb": "21", "codcan": "2", "sorteo": "3", "cedula": "51992648", "nomcan": "CLAUDIA", "apecan": "LÓPEZ", "nomcan2": "LEONARDO HUMBERTO", "apecan2": "HUERTA GUTIÉRREZ", "vot": "1229", "pvot": "0,24%", "carg": "0", "pref": "1", "empate": "0"}]}}, {"act": {"codpar": "14", "cam": "0", "vot": "917", "pvot": "0,18%", "carg": "0", "cargElectos": "0", "cargEmpatados": "0", "cantotabla": [{"amb": "21", "codcan": "5", "sorteo": "6", "cedula": "79960663", "nomcan": "ÓSCAR MAURICIO", "apecan": "LIZCANO ARANGO", "nomcan2": "PEDRO LUIS", "apecan2": "DE LA TORRE MARQUEZ", "vot": "917", "pvot": "0,18%", "carg": "0", "pref": "1", "empate": "0"}]}}, {"act": {"codpar": "9", "cam": "0", "vot": "428", "pvot": "0,08%", "carg": "0", "cargElectos": "0", "cargEmpatados": "0", "cantotabla": [{"amb": "21", "codcan": "7", "sorteo": "8", "cedula": "66921526", "nomcan": "SONDRA MACOLLINS", "apecan": "GARVIN PINTO", "nomcan2": "LEONARDO", "apecan2": "KARAM HELO", "vot": "428", "pvot": "0,08%", "carg": "0", "pref": "1", "empate": "0"}]}}, {"act": {"codpar": "4", "cam": "0", "vot": "420", "pvot": "0,08%", "carg": "0", "cargElectos": "0", "cargEmpatados": "0", "cantotabla": [{"amb": "21", "codcan": "6", "sorteo": "7", "cedula": "8319134", "nomcan": "MIGUEL", "apecan": "URIBE LONDOÑO", "nomcan2": "LUISA FERNANDA", "apecan2": "VILLEGAS ARAQUE", "vot": "420", "pvot": "0,08%", "carg": "0", "pref": "1", "empate": "0"}]}}, {"act": {"codpar": "6", "cam": "0", "vot": "238", "pvot": "0,04%", "carg": "0", "cargElectos": "0", "cargEmpatados": "0", "cantotabla": [{"amb": "21", "codcan": "8", "sorteo": "9", "cedula": "79289575", "nomcan": "ROY LEONARDO", "apecan": "BARRERAS MONTEALEGRE", "nomcan2": "MARTHA LUCÍA", "apecan2": "ZAMORA ÁVILA", "vot": "238", "pvot": "0,04%", "carg": "0", "pref": "1", "empate": "0"}]}}, {"act": {"codpar": "12", "cam": "0", "vot": "213", "pvot": "0,04%", "carg": "0", "cargElectos": "0", "cargEmpatados": "0", "cantotabla": [{"amb": "21", "codcan": "13", "sorteo": "14", "cedula": "11794488", "nomcan": "LUIS GILBERTO", "apecan": "MURILLO URRUTIA", "nomcan2": "LUZ MARÍA", "apecan2": "ZAPATA ZAPATA", "vot": "213", "pvot": "0,04%", "carg": "0", "pref": "1", "empate": "0"}]}}, {"act": {"codpar": "5", "cam": "0", "vot": "121", "pvot": "0,02%", "carg": "0", "cargElectos": "0", "cargEmpatados": "0", "cantotabla": [{"amb": "21", "codcan": "10", "sorteo": "11", "cedula": "79140442", "nomcan": "GUSTAVO", "apecan": "MATAMOROS CAMACHO", "nomcan2": "MILA MARÍA", "apecan2": "PAZ CAMPAZ", "vot": "121", "pvot": "0,02%", "carg": "0", "pref": "1", "empate": "0"}]}}], "mapagan": [{"amb": "21008", "codpar": "7", "vot": "3585", "pvot": "72,96%", "votant": "4953", "pvotant": "44,39%", "votcan": "4850", "mesesc": "35", "pmesesc": "100%", "carg": "0", "nombre": "ALGARROBO", "hayEmpate": "0", "cantotabla": {"codcan": "1", "sorteo": "1", "nomcan": "IVÁN", "apecan": "CEPEDA CASTRO", "nomcan2": "AIDA MARINA", "apecan2": "QUILCUE VIVAS"}}, {"amb": "21010", "codpar": "7", "vot": "7645", "pvot": "61,70%", "votant": "12494", "pvotant": "40,83%", "votcan": "12182", "mesesc": "93", "pmesesc": "100%", "carg": "0", "nombre": "ARACATACA", "hayEmpate": "0", "cantotabla": {"codcan": "1", "sorteo": "1", "nomcan": "IVÁN", "apecan": "CEPEDA CASTRO", "nomcan2": "AIDA MARINA", "apecan2": "QUILCUE VIVAS"}}, {"amb": "21012", "codpar": "10", "vot": "5232", "pvot": "46,31%", "votant": "11450", "pvotant": "46,48%", "votcan": "11153", "mesesc": "73", "pmesesc": "100%", "carg": "0", "nombre": "ARIGUANI (EL DIFICIL)", "hayEmpate": "0", "cantotabla": {"codcan": "4", "sorteo": "5", "nomcan": "ABELARDO", "apecan": "DE LA ESPRIELLA", "nomcan2": "JOSÉ MANUEL", "apecan2": "RESTREPO ABONDANO"}}, {"amb": "21013", "codpar": "10", "vot": "1769", "pvot": "54,09%", "votant": "3299", "pvotant": "35,95%", "votcan": "3250", "mesesc": "28", "pmesesc": "100%", "carg": "0", "nombre": "CERRO DE SAN ANTONIO", "hayEmpate": "0", "cantotabla": {"codcan": "4", "sorteo": "5", "nomcan": "ABELARDO", "apecan": "DE LA ESPRIELLA", "nomcan2": "JOSÉ MANUEL", "apecan2": "RESTREPO ABONDANO"}}, {"amb": "21015", "codpar": "10", "vot": "3685", "pvot": "53,54%", "votant": "6929", "pvotant": "43,65%", "votcan": "6808", "mesesc": "47", "pmesesc": "100%", "carg": "0", "nombre": "CHIVOLO", "hayEmpate": "0", "cantotabla": {"codcan": "4", "sorteo": "5", "nomcan": "ABELARDO", "apecan": "DE LA ESPRIELLA", "nomcan2": "JOSÉ MANUEL", "apecan2": "RESTREPO ABONDANO"}}, {"amb": "21016", "codpar": "7", "vot": "25967", "pvot": "59,95%", "votant": "43832", "pvotant": "46,42%", "votcan": "42524", "mesesc": "271", "pmesesc": "100%", "carg": "0", "nombre": "CIENAGA", "hayEmpate": "0", "cantotabla": {"codcan": "1", "sorteo": "1", "nomcan": "IVÁN", "apecan": "CEPEDA CASTRO", "nomcan2": "AIDA MARINA", "apecan2": "QUILCUE VIVAS"}}, {"amb": "21020", "codpar": "7", "vot": "2414", "pvot": "55,00%", "votant": "4418", "pvotant": "35,48%", "votcan": "4363", "mesesc": "37", "pmesesc": "100%", "carg": "0", "nombre": "CONCORDIA", "hayEmpate": "0", "cantotabla": {"codcan": "1", "sorteo": "1", "nomcan": "IVÁN", "apecan": "CEPEDA CASTRO", "nomcan2": "AIDA MARINA", "apecan2": "QUILCUE VIVAS"}}, {"amb": "21025", "codpar": "10", "vot": "11876", "pvot": "53,12%", "votant": "22571", "pvotant": "43,43%", "votcan": "22127", "mesesc": "159", "pmesesc": "100%", "carg": "0", "nombre": "EL BANCO", "hayEmpate": "0", "cantotabla": {"codcan": "4", "sorteo": "5", "nomcan": "ABELARDO", "apecan": "DE LA ESPRIELLA", "nomcan2": "JOSÉ MANUEL", "apecan2": "RESTREPO ABONDANO"}}, {"amb": "21028", "codpar": "7", "vot": "2868", "pvot": "49,38%", "votant": "5849", "pvotant": "41,35%", "votcan": "5744", "mesesc": "44", "pmesesc": "100%", "carg": "0", "nombre": "EL PIÑON", "hayEmpate": "0", "cantotabla": {"codcan": "1", "sorteo": "1", "nomcan": "IVÁN", "apecan": "CEPEDA CASTRO", "nomcan2": "AIDA MARINA", "apecan2": "QUILCUE VIVAS"}}, {"amb": "21030", "codpar": "7", "vot": "5223", "pvot": "75,98%", "votant": "6939", "pvotant": "41,40%", "votcan": "6779", "mesesc": "49", "pmesesc": "100%", "carg": "0", "nombre": "EL RETEN", "hayEmpate": "0", "cantotabla": {"codcan": "1", "sorteo": "1", "nomcan": "IVÁN", "apecan": "CEPEDA CASTRO", "nomcan2": "AIDA MARINA", "apecan2": "QUILCUE VIVAS"}}, {"amb": "21031", "codpar": "7", "vot": "11518", "pvot": "47,06%", "votant": "24745", "pvotant": "41,35%", "votcan": "24118", "mesesc": "167", "pmesesc": "100%", "carg": "0", "nombre": "FUNDACION", "hayEmpate": "0", "cantotabla": {"codcan": "1", "sorteo": "1", "nomcan": "IVÁN", "apecan": "CEPEDA CASTRO", "nomcan2": "AIDA MARINA", "apecan2": "QUILCUE VIVAS"}}, {"amb": "21040", "codpar": "10", "vot": "5965", "pvot": "57,72%", "votant": "10388", "pvotant": "42,11%", "votcan": "10248", "mesesc": "79", "pmesesc": "100%", "carg": "0", "nombre": "GUAMAL", "hayEmpate": "0", "cantotabla": {"codcan": "4", "sorteo": "5", "nomcan": "ABELARDO", "apecan": "DE LA ESPRIELLA", "nomcan2": "JOSÉ MANUEL", "apecan2": "RESTREPO ABONDANO"}}, {"amb": "21042", "codpar": "10", "vot": "4128", "pvot": "54,21%", "votant": "7678", "pvotant": "44,45%", "votcan": "7514", "mesesc": "52", "pmesesc": "100%", "carg": "0", "nombre": "NUEVA GRANADA", "hayEmpate": "0", "cantotabla": {"codcan": "4", "sorteo": "5", "nomcan": "ABELARDO", "apecan": "DE LA ESPRIELLA", "nomcan2": "JOSÉ MANUEL", "apecan2": "RESTREPO ABONDANO"}}, {"amb": "21046", "codpar": "10", "vot": "2096", "pvot": "55,24%", "votant": "3846", "pvotant": "34,79%", "votcan": "3768", "mesesc": "33", "pmesesc": "100%", "carg": "0", "nombre": "PEDRAZA", "hayEmpate": "0", "cantotabla": {"codcan": "4", "sorteo": "5", "nomcan": "ABELARDO", "apecan": "DE LA ESPRIELLA", "nomcan2": "JOSÉ MANUEL", "apecan2": "RESTREPO ABONDANO"}}, {"amb": "21048", "codpar": "10", "vot": "2588", "pvot": "55,18%", "votant": "4729", "pvotant": "47,13%", "votcan": "4635", "mesesc": "35", "pmesesc": "100%", "carg": "0", "nombre": "PIJIÑO DEL CARMEN", "hayEmpate": "0", "cantotabla": {"codcan": "4", "sorteo": "5", "nomcan": "ABELARDO", "apecan": "DE LA ESPRIELLA", "nomcan2": "JOSÉ MANUEL", "apecan2": "RESTREPO ABONDANO"}}, {"amb": "21049", "codpar": "7", "vot": "7442", "pvot": "56,89%", "votant": "13228", "pvotant": "42,52%", "votcan": "12918", "mesesc": "94", "pmesesc": "100%", "carg": "0", "nombre": "PIVIJAY", "hayEmpate": "0", "cantotabla": {"codcan": "1", "sorteo": "1", "nomcan": "IVÁN", "apecan": "CEPEDA CASTRO", "nomcan2": "AIDA MARINA", "apecan2": "QUILCUE VIVAS"}}, {"amb": "21052", "codpar": "7", "vot": "10745", "pvot": "54,99%", "votant": "19713", "pvotant": "44,73%", "votcan": "19334", "mesesc": "131", "pmesesc": "100%", "carg": "0", "nombre": "PLATO", "hayEmpate": "0", "cantotabla": {"codcan": "1", "sorteo": "1", "nomcan": "IVÁN", "apecan": "CEPEDA CASTRO", "nomcan2": "AIDA MARINA", "apecan2": "QUILCUE VIVAS"}}, {"amb": "21055", "codpar": "7", "vot": "4940", "pvot": "60,95%", "votant": "8209", "pvotant": "35,97%", "votcan": "7991", "mesesc": "69", "pmesesc": "100%", "carg": "0", "nombre": "PUEBLOVIEJO", "hayEmpate": "0", "cantotabla": {"codcan": "1", "sorteo": "1", "nomcan": "IVÁN", "apecan": "CEPEDA CASTRO", "nomcan2": "AIDA MARINA", "apecan2": "QUILCUE VIVAS"}}, {"amb": "21058", "codpar": "7", "vot": "2364", "pvot": "65,84%", "votant": "3610", "pvotant": "46,45%", "votcan": "3557", "mesesc": "26", "pmesesc": "100%", "carg": "0", "nombre": "REMOLINO", "hayEmpate": "0", "cantotabla": {"codcan": "1", "sorteo": "1", "nomcan": "IVÁN", "apecan": "CEPEDA CASTRO", "nomcan2": "AIDA MARINA", "apecan2": "QUILCUE VIVAS"}}, {"amb": "21060", "codpar": "10", "vot": "2687", "pvot": "49,22%", "votant": "5502", "pvotant": "43,31%", "votcan": "5406", "mesesc": "42", "pmesesc": "100%", "carg": "0", "nombre": "SABANAS DE SAN ANGEL", "hayEmpate": "0", "cantotabla": {"codcan": "4", "sorteo": "5", "nomcan": "ABELARDO", "apecan": "DE LA ESPRIELLA", "nomcan2": "JOSÉ MANUEL", "apecan2": "RESTREPO ABONDANO"}}, {"amb": "21067", "codpar": "7", "vot": "2013", "pvot": "51,92%", "votant": "3895", "pvotant": "45,93%", "votcan": "3827", "mesesc": "25", "pmesesc": "100%", "carg": "0", "nombre": "SALAMINA", "hayEmpate": "0", "cantotabla": {"codcan": "1", "sorteo": "1", "nomcan": "IVÁN", "apecan": "CEPEDA CASTRO", "nomcan2": "AIDA MARINA", "apecan2": "QUILCUE VIVAS"}}, {"amb": "21070", "codpar": "10", "vot": "4425", "pvot": "54,70%", "votant": "8129", "pvotant": "44,75%", "votcan": "8017", "mesesc": "58", "pmesesc": "100%", "carg": "0", "nombre": "SAN SEBASTIAN DE BUENAVISTA", "hayEmpate": "0", "cantotabla": {"codcan": "4", "sorteo": "5", "nomcan": "ABELARDO", "apecan": "DE LA ESPRIELLA", "nomcan2": "JOSÉ MANUEL", "apecan2": "RESTREPO ABONDANO"}}, {"amb": "21073", "codpar": "10", "vot": "1888", "pvot": "42,18%", "votant": "4496", "pvotant": "47,17%", "votcan": "4439", "mesesc": "32", "pmesesc": "100%", "carg": "0", "nombre": "SAN ZENON", "hayEmpate": "0", "cantotabla": {"codcan": "4", "sorteo": "5", "nomcan": "ABELARDO", "apecan": "DE LA ESPRIELLA", "nomcan2": "JOSÉ MANUEL", "apecan2": "RESTREPO ABONDANO"}}, {"amb": "21076", "codpar": "10", "vot": "5794", "pvot": "66,95%", "votant": "8699", "pvotant": "48,60%", "votcan": "8585", "mesesc": "55", "pmesesc": "100%", "carg": "0", "nombre": "SANTA ANA", "hayEmpate": "0", "cantotabla": {"codcan": "4", "sorteo": "5", "nomcan": "ABELARDO", "apecan": "DE LA ESPRIELLA", "nomcan2": "JOSÉ MANUEL", "apecan2": "RESTREPO ABONDANO"}}, {"amb": "21078", "codpar": "7", "vot": "2323", "pvot": "57,69%", "votant": "4053", "pvotant": "43,55%", "votcan": "3984", "mesesc": "29", "pmesesc": "100%", "carg": "0", "nombre": "SANTA BARBARA DE PINTO", "hayEmpate": "0", "cantotabla": {"codcan": "1", "sorteo": "1", "nomcan": "IVÁN", "apecan": "CEPEDA CASTRO", "nomcan2": "AIDA MARINA", "apecan2": "QUILCUE VIVAS"}}, {"amb": "21001", "codpar": "7", "vot": "112812", "pvot": "52,40%", "votant": "217221", "pvotant": "53,12%", "votcan": "211364", "mesesc": "1176", "pmesesc": "100%", "carg": "0", "nombre": "SANTA MARTA", "hayEmpate": "0", "cantotabla": {"codcan": "1", "sorteo": "1", "nomcan": "IVÁN", "apecan": "CEPEDA CASTRO", "nomcan2": "AIDA MARINA", "apecan2": "QUILCUE VIVAS"}}, {"amb": "21079", "codpar": "7", "vot": "4427", "pvot": "59,40%", "votant": "7533", "pvotant": "34,34%", "votcan": "7366", "mesesc": "65", "pmesesc": "100%", "carg": "0", "nombre": "SITIONUEVO", "hayEmpate": "0", "cantotabla": {"codcan": "1", "sorteo": "1", "nomcan": "IVÁN", "apecan": "CEPEDA CASTRO", "nomcan2": "AIDA MARINA", "apecan2": "QUILCUE VIVAS"}}, {"amb": "21085", "codpar": "7", "vot": "2740", "pvot": "55,05%", "votant": "5027", "pvotant": "41,10%", "votcan": "4913", "mesesc": "40", "pmesesc": "100%", "carg": "0", "nombre": "TENERIFE", "hayEmpate": "0", "cantotabla": {"codcan": "1", "sorteo": "1", "nomcan": "IVÁN", "apecan": "CEPEDA CASTRO", "nomcan2": "AIDA MARINA", "apecan2": "QUILCUE VIVAS"}}, {"amb": "21090", "codpar": "10", "vot": "2435", "pvot": "62,37%", "votant": "3940", "pvotant": "42,49%", "votcan": "3872", "mesesc": "31", "pmesesc": "100%", "carg": "0", "nombre": "ZAPAYAN", "hayEmpate": "0", "cantotabla": {"codcan": "4", "sorteo": "5", "nomcan": "ABELARDO", "apecan": "DE LA ESPRIELLA", "nomcan2": "JOSÉ MANUEL", "apecan2": "RESTREPO ABONDANO"}}, {"amb": "21095", "codpar": "7", "vot": "14635", "pvot": "72,06%", "votant": "20618", "pvotant": "40,22%", "votcan": "19998", "mesesc": "153", "pmesesc": "100%", "carg": "0", "nombre": "ZONA BANANERA (SEVILLA)", "hayEmpate": "0", "cantotabla": {"codcan": "1", "sorteo": "1", "nomcan": "IVÁN", "apecan": "CEPEDA CASTRO", "nomcan2": "AIDA MARINA", "apecan2": "QUILCUE VIVAS"}}]}], "historico": [{"numact": "18", "numdep": "18", "mdhm": "05311734", "mesesc": "3223", "mesfalt": "5", "pvotant": ""}, {"numact": "17", "numdep": "17", "mdhm": "05311729", "mesesc": "3215", "mesfalt": "13", "pvotant": ""}, {"numact": "16", "numdep": "16", "mdhm": "05311724", "mesesc": "3201", "mesfalt": "27", "pvotant": ""}, {"numact": "15", "numdep": "15", "mdhm": "05311719", "mesesc": "3173", "mesfalt": "55", "pvotant": ""}, {"numact": "14", "numdep": "14", "mdhm": "05311714", "mesesc": "3125", "mesfalt": "103", "pvotant": ""}, {"numact": "13", "numdep": "13", "mdhm": "05311709", "mesesc": "3062", "mesfalt": "166", "pvotant": ""}, {"numact": "12", "numdep": "12", "mdhm": "05311703", "mesesc": "2956", "mesfalt": "272", "pvotant": ""}, {"numact": "11", "numdep": "11", "mdhm": "05311658", "mesesc": "2730", "mesfalt": "498", "pvotant": ""}, {"numact": "10", "numdep": "10", "mdhm": "05311653", "mesesc": "2359", "mesfalt": "869", "pvotant": ""}, {"numact": "9", "numdep": "9", "mdhm": "05311648", "mesesc": "1908", "mesfalt": "1320", "pvotant": ""}, {"numact": "8", "numdep": "8", "mdhm": "05311643", "mesesc": "1457", "mesfalt": "1771", "pvotant": ""}, {"numact": "7", "numdep": "7", "mdhm": "05311638", "mesesc": "1005", "mesfalt": "2223", "pvotant": ""}, {"numact": "6", "numdep": "6", "mdhm": "05311633", "mesesc": "591", "mesfalt": "2637", "pvotant": ""}, {"numact": "5", "numdep": "5", "mdhm": "05311628", "mesesc": "304", "mesfalt": "2924", "pvotant": ""}, {"numact": "4", "numdep": "4", "mdhm": "05311623", "mesesc": "137", "mesfalt": "3091", "pvotant": ""}, {"numact": "3", "numdep": "3", "mdhm": "05311618", "mesesc": "54", "mesfalt": "3174", "pvotant": ""}, {"numact": "2", "numdep": "2", "mdhm": "05311613", "mesesc": "15", "mesfalt": "3213", "pvotant": ""}, {"numact": "1", "numdep": "1", "mdhm": "05311608", "mesesc": "1", "mesfalt": "3227", "pvotant": ""}, {"numact": "0", "numdep": "0", "mdhm": "05311600", "mesesc": "0", "mesfalt": "3228", "pvotant": ""}], "dept": "21"}